l5_shoppinglist/__init__.py
l5_shoppinglist/__main__.py
l5_shoppinglist/db/shoppinglist_template_db.json
l5_shoppinglist-20.2.1.dist-info/LICENSE
l5_shoppinglist-20.2.1.dist-info/WHEEL
l5_shoppinglist-20.2.1.dist-info/METADATA
l5_shoppinglist-20.2.1.dist-info/RECORD
