Metadata-Version: 2.1
Name: l5_shoppinglist
Version: 20.2.1
Summary: gtk l5_shoppinglist
Home-page: https://source.puri.sm/fphemeral/l5_shoppinglist
License: UNKNOWN
Author: fphemeral
Author-email: fphemeral@i2pmail.org
Requires-Python: >=3.7
Classifier: License :: OSI Approved :: GNU General Public License v3 or later (GPLv3+)
Requires-Dist: tinydb>=3.15.2
Requires-Dist: PyGObject
